moneyprinter/__init__.py
moneyprinter/moneyprinter.py
moneyprintergobrrr-0.3.dist-info/LICENSE.txt
moneyprintergobrrr-0.3.dist-info/METADATA
moneyprintergobrrr-0.3.dist-info/WHEEL
moneyprintergobrrr-0.3.dist-info/top_level.txt
moneyprintergobrrr-0.3.dist-info/RECORD
