Metadata-Version: 2.1
Name: moneyprintergobrrr
Version: 0.3
Summary: Money printer go brr
Home-page: https://github.com/mkmozgawa/moneyprintergobrrr
Author: Magda Mozgawa
Author-email: mkmozgawa@gmail.com
License: MIT
Download-URL: https://pypi.org/project/moneyprintergobrrr/
Keywords: Moneyprinter,Money printer,brrr,meme
Platform: UNKNOWN
